{
  "columns": [
    "Class",
    "Images",
    "Objects",
    "Count on image, average",
    "Area on image, average (%)"
  ],
  "data": [
    [
      "transverse",
      945,
      1093,
      1.1566,
      11.9777
    ],
    [
      "alligator",
      510,
      627,
      1.2294,
      35.4144
    ],
    [
      "longitudinal",
      520,
      601,
      1.1558,
      8.4718
    ],
    [
      "sealed",
      328,
      426,
      1.2988,
      15.1582
    ]
  ],
  "description": "Images column counts images containing at least one object of class.",
  "options": {
    "sort": {
      "columnIndex": 2,
      "order": "desc"
    },
    "pageSize": 100
  }
}